{"version":1,"resource":"file:///d%3A/madoodia/dev/UE_Projects/UE5_UI_Demo/Source/UE5_UI_Demo/UE5_UI_Demo.h","entries":[{"id":"HxqT.h","timestamp":1674438279962},{"id":"0pXS.h","timestamp":1674438368521},{"id":"iayr.h","timestamp":1674438439503},{"id":"obex.h","timestamp":1674438487265},{"id":"B9O8.h","timestamp":1674438597180},{"id":"bHAy.h","timestamp":1674438733649},{"id":"BZe9.h","timestamp":1674438784754},{"id":"Ex7y.h","timestamp":1674454034690},{"id":"4MrE.h","timestamp":1674454064405},{"id":"IFCa.h","timestamp":1674454322706},{"id":"LVDZ.h","timestamp":1674455372424}]}