{"version":1,"resource":"file:///d%3A/madoodia/dev/Zolf/CMakeLists.txt","entries":[{"id":"wYUI.txt","timestamp":1667452243913},{"id":"GXPD.txt","timestamp":1667454197643},{"id":"ojA8.txt","timestamp":1667454219173},{"id":"4iK3.txt","timestamp":1667454307689},{"id":"vtaK.txt","source":"undoRedo.source","timestamp":1667454348680},{"id":"eZa5.txt","timestamp":1667454406579},{"id":"oWgC.txt","timestamp":1667454806187},{"id":"rGp7.txt","source":"undoRedo.source","timestamp":1667454842818},{"id":"Fl4z.txt","timestamp":1667455538845}]}